Magpy/MagmaPropertiesChecker.py
Magpy/Magmas.py
Magpy/RandSampMags.py
Magpy/__init__.py
MagpyCAS-1.0.12.dist-info/LICENSE
MagpyCAS-1.0.12.dist-info/METADATA
MagpyCAS-1.0.12.dist-info/WHEEL
MagpyCAS-1.0.12.dist-info/top_level.txt
MagpyCAS-1.0.12.dist-info/RECORD
