Metadata-Version: 2.1
Name: MagpyCAS
Version: 1.0.12
Summary: A primitive package for creating mathematical structures from magmas to abelian groups, and determining their properties. 
Author: Skylar Korf
Author-email: skorf60@gmail.com
License-File: LICENSE
Requires-Dist: iteration-utilities
